odoo/addons/sequence_check_digit/README.rst
odoo/addons/sequence_check_digit/__init__.py
odoo/addons/sequence_check_digit/__manifest__.py
odoo/addons/sequence_check_digit/i18n/es.po
odoo/addons/sequence_check_digit/i18n/sequence_check_digit.pot
odoo/addons/sequence_check_digit/models/__init__.py
odoo/addons/sequence_check_digit/models/ir_sequence.py
odoo/addons/sequence_check_digit/readme/CONTRIBUTORS.rst
odoo/addons/sequence_check_digit/readme/DESCRIPTION.rst
odoo/addons/sequence_check_digit/readme/USAGE.rst
odoo/addons/sequence_check_digit/static/description/icon.png
odoo/addons/sequence_check_digit/static/description/index.html
odoo/addons/sequence_check_digit/tests/__init__.py
odoo/addons/sequence_check_digit/tests/test_check_digit.py
odoo/addons/sequence_check_digit/views/sequence_views.xml
odoo12_addon_sequence_check_digit-12.0.1.0.0.99.dev5.dist-info/METADATA
odoo12_addon_sequence_check_digit-12.0.1.0.0.99.dev5.dist-info/WHEEL
odoo12_addon_sequence_check_digit-12.0.1.0.0.99.dev5.dist-info/top_level.txt
odoo12_addon_sequence_check_digit-12.0.1.0.0.99.dev5.dist-info/RECORD
